<?xml version="1.0" encoding="utf-8"?>
<odoo>

<template id="snippet_options" inherit_id="website.snippet_options" name="Wishlist Snippet Options">
    <xpath expr="." position="inside">
        <div data-selector="#wrapwrap > header"
            data-no-check="true"
            groups="website.group_website_designer">
            <we-checkbox string="Show Empty Wishlist"
                         data-customize-website-views="website_sale_wishlist.header_hide_empty_wishlist_link|"
                         data-no-preview="true"
                         data-reload="/"/>
        </div>
        <div data-selector="#products_grid .o_wsale_products_grid_table_wrapper > table"
            data-no-check="true"
            groups="website.group_website_designer">
            <we-checkbox string="Wishlist Button"
                         data-customize-website-views="website_sale_wishlist.add_to_wishlist"
                         data-no-preview="true"
                         data-reload="/"/>
        </div>
        <div data-selector=".js_sale #product_details" data-no-check="true">
            <we-checkbox string="Wishlist Button"
                         data-customize-website-views="website_sale_wishlist.product_add_to_wishlist"
                         data-no-preview="true"
                         data-reload="/"/>
        </div>
    </xpath>
</template>

</odoo>
